[
  { "topic": "Mass Media" , 
    "groups": ["article,advertisement,interview,celebration",
               "news,headline,review,editorial",
               "publisher,editor,journalist,critic"],
    "answer" : "0"},
  { "topic": "Plants" , 
    "groups": ["pine,fur,larch,cedar",
              "oak,birch,chestnut,alder",
              "weed,greenery,grass,herb"],
    "answer" : "0"},
    { "topic": "Books and Reading" , 
      "groups": ["dictionary,reference-book,brochure,manual",
                "novel,fairy-tale,fiction,thriller",
                "bibliography,supplement,contests,conclusion"],
      "answer" : "2"}
]